{
  "StRgzOyi": "./js/themes/slots-light.js",
  "CHWK3Ij4": "./js/components/select",
  "JIwte8kz": "./js/themes/livecasino-light.js",
  "Ko1w5bLQ": "./js/components/inline",
  "ajVmZVN9": "./js/themes/luckyslots.js",
  "1v6zGokT": "./js/components/text",
  "ik1RYx5F": "./js/themes/bombay-club.js",
  "UTJkgazk": "./js/themes/moon-design-dark.js",
  "ZkAT0WW5": "./js/themes/btcxe.js",
  "GXrLXNR6": "./js/components/carousel",
  "d111A9ix": "./js/assets/pattern",
  "FI9OoztD": "./js/assets/icon",
  "e7MKwHQ9": "./js/components/link",
  "05vLBSYs": "./js/components/badge",
  "UzJpwBd1": "./js/assets/duotone",
  "qbS99Svo": "./js/themes/bitcasino-light.js",
  "OZWjjZRc": "./js/themes/sportsbet-light.js",
  "RLBob2QU": "./js/themes/slots-dark.js",
  "PyCcKZNV": "./js/components/checkbox",
  "qfswhgL2": "./js/themes/moon-design-light.js",
  "nFsVcOR9": "./js/components/button",
  "OhFMMglt": "./js/themes/missions-tool-dark.js",
  "p2TZqouh": "./js/assets/logo",
  "wrUcpnSs": "./js/themes/aposta10-dark.js",
  "XtY9uICR": "./js/app.js",
  "8orDc519": "./js/themes/missions-tool-light.js",
  "fHRF6mHw": "./js/components/stack",
  "hSBbZC1M": "./js/themes/bitcasino-dark.js",
  "HgwHDu3a": "./js/assets/crest",
  "gYx2uAWj": "./js/components/text-input",
  "iowyttp3": "./js/themes/livecasino-dark.js",
  "X6Oe3ES2": "./js/themes/sportsbet-dark.js",
  "ft3SxKML": "./js/themes/aposta10-light.js",
  "aXg4M8yA": "./js/themes/hub88.js",
  "Fx2MqhD5": "./js/components/heading",
  "qWpOkhuQ": "./js/components/avatar"
}